ai_tools_z/__init__.py
ai_tools_z/plg_install.py
ai_tools_z/大语言模型提示词.py
ai_tools_z/查看编辑coco标注.py
ai_tools_z/data_anay/__init__.py
ai_tools_z/data_anay/kmeans.py
ai_tools_z/data_anay/polyfit.py
ai_tools_z/ifly/__init__.py
ai_tools_z/ifly/api/__init__.py
ai_tools_z/ifly/api/config.py
ai_tools_z/ifly/api/General/__init__.py
ai_tools_z/ifly/api/General/单句对话_http.py
ai_tools_z/ifly/api/General/单句对话_ws.py
ai_tools_z/ifly/api/General/chat/SparkApi.py
ai_tools_z/ifly/api/General/chat/__init__.py
ai_tools_z/ifly/api/General/chat/chat_demo.py
ai_tools_z/ifly/api/selfLLM/__init__.py
ai_tools_z/ifly/api/selfLLM/单句对话_ws_回调式.py
ai_tools_z/ifly/api/selfLLM/单句对话_ws_阻塞式.py
ai_tools_z/ifly/prepare_train_data/__init__.py
ai_tools_z/ifly/prepare_train_data/pd2jonsl.py
ai_tools_z/ifly/prepare_train_data/to_jsonl.py
ai_tools_z/step1_data_prepare/__init__.py
ai_tools_z/step1_data_prepare/image/__init__.py
ai_tools_z/step1_data_prepare/image/多张图片_合成_视频.py
ai_tools_z/step1_data_prepare/image/视频_提取_帧图片.py
ai_tools_z/step1_data_prepare/nlp/__init__.py
ai_tools_z/step1_data_prepare/nlp/pre_process.py
ai_tools_z/step1_data_prepare/nlp/remove_error_encode.py
ai_tools_z/visualize/__init__.py
ai_tools_z/visualize/多图标.py
ai_tools_z/visualize/折线图.py
ai_tools_z/visualize/柱状图.py
ai_tools_z/yolo/__init__.py
ai_tools_z/yolo/yolo_results保存.py
ai_tools_z/yolo/yolov10_img标注.py
ai_tools_z/yolo/yolov10_video测试.py
ai_tools_z-2.5.dist-info/METADATA
ai_tools_z-2.5.dist-info/WHEEL
ai_tools_z-2.5.dist-info/top_level.txt
ai_tools_z-2.5.dist-info/RECORD
