Metadata-Version: 2.1
Name: ai-tools-z
Version: 2.5
Summary: 常用的人工智能操作的中文工具包。0728
Home-page: https://github.com/sunshine/
Author: Liu Xing
Author-email: 
Classifier: Programming Language :: Python :: 3.8
Classifier: License :: OSI Approved :: MIT License
Classifier: Operating System :: OS Independent
Requires-Dist: xlwt
Requires-Dist: psutil
Requires-Dist: ultralytics
Requires-Dist: opencv-python
Requires-Dist: matplotlib
Requires-Dist: tqdm
Requires-Dist: pycocotools
Requires-Dist: websocket-client
Requires-Dist: openpyxl
Requires-Dist: openai
Requires-Dist: emoji
Requires-Dist: jieba
